{
  "name": "resized/a2c75f73-b074-437a-ad0b-c3177ffca2b1_2400x1600",
  "bucket": "birch-collective-develop.appspot.com",
  "metageneration": 1,
  "generation": 1688381192554,
  "contentType": "image/webp",
  "storageClass": "STANDARD",
  "contentDisposition": "",
  "downloadTokens": ["0b99c6fd-087b-4018-8813-5bc2b44d9824"],
  "etag": "s9KtuGb+EKxrlwwGbNc/CTCNuus",
  "customMetadata": {
    "resizedImage": "true"
  },
  "timeCreated": "2023-07-03T10:46:32.554Z",
  "updated": "2023-07-03T10:46:32.554Z",
  "size": 50902,
  "md5Hash": "OoR83DDIg+fi1SfmdDEGQg==",
  "crc32c": "4182208173"
}
